{
  "cate": "6",
  "date": "11æ17æ¥ 20æ29å",
  "datetime": "2018-11-17T20:29",
  "video": "/news/html/20181117/movie/k10011714711_201811172056_201811172056.html",
  "duration": 65,
  "img": "html/20181117/K10011714711_1811172032_1811172033_01_02.jpg",
  "title": "トイレ拭いた雑巾でコップを… 中国の高級ホテルが謝罪",
  "summary": "中国にある五つ星を含めた14の高級ホテルで、清掃員が、トイレを拭いた雑巾でコップも拭くなど、ずさんな清掃活動を撮影した映像が公開されました。一部のホテルは謝罪に追い込まれ、中国当局が調査に乗り出しました。",
  "more": "この映像は、中国の高級ホテルでずさんな清掃活動が横行しているのを告発するとして、このほど、中国版ツイッターの「ウェイボー」で公開されました。<br /><br />投稿者は、みずから泊まったホテルにカメラを隠して撮影したということで、ホテルの清掃員が、客が使用したバスタオルでコップを拭いたり、洗面台やトイレなどを拭いた雑巾でコップも拭く様子などが映っています。<br /><br />中国メディアによりますと、こうしたずさんな清掃は、複数の五つ星ホテルを含めて、合わせて14の高級ホテルで確認されたということです。<br /><br />インターネット上では、衛生面への不安から、「恐ろしすぎる」とか、「五つ星のホテルでこれなら、ほかのホテルでもきっとこうした清掃が行われているだろう」といった批判が高まっています。<br /><br />この事態を受けて、一部のホテルは謝罪に追い込まれ、当局は、問題が指摘されたホテルに対して調査に乗り出しました。",
  "body": [
    {
      "title": "",
      "img": "",
      "align": "",
      "text": "",
      "textPos": ""
    }
  ],
  "relationNews": [],
  "relationLink": [],
  "word": [],
  "news_id": "k10011714711000",
  "yyyy": "2018",
  "mm": "11",
  "dd": "17",
  "url": "https://www3.nhk.or.jp/news/html/20181117/k10011714711000.html?utm_int=news-new_contents_list-items_001"
}