{
  "reikai": {
    "entries": {
      "0000": [
        {
          "def": "１９８９<ruby><rb>年</rb><rt>ねん</rt></ruby><ruby><rb>１月８日</rb><rt>いちがつようか</rt></ruby>からあとの、<ruby><rb>日本</rb><rt>にっぽん</rt></ruby>の<ruby><rb>年号</rb><rt>ねんごう</rt></ruby>。",
          "hyouki": [
            "平成"
          ]
        }
      ],
      "0001": [
        {
          "def": "<ruby><rb>日本</rb><rt>にっぽん</rt></ruby>の<ruby><rb>国</rb><rt>くに</rt></ruby>の<ruby><rb>象徴</rb><rt>しょうちょう</rt></ruby>としてあおがれている<ruby><rb>人</rb><rt>ひと</rt></ruby>。",
          "hyouki": [
            "天皇"
          ]
        }
      ],
      "0002": [
        {
          "def": "<ruby><rb>天皇</rb><rt>てんのう</rt></ruby>や<ruby><rb>皇后</rb><rt>こうごう</rt></ruby>などを<ruby><rb>敬</rb><rt>うやま</rt></ruby>って<ruby><rb>呼</rb><rt>よ</rt></ruby>ぶことば。",
          "hyouki": [
            "陛下"
          ]
        }
      ],
      "0003": [
        {
          "def": "<ruby><rb>国王</rb><rt>こくおう</rt></ruby>などが<ruby><rb>位</rb><rt>くらい</rt></ruby>を<ruby><rb>退</rb><rt>しりぞ</rt></ruby>くこと。",
          "hyouki": [
            "退位"
          ]
        }
      ],
      "0004": [
        {
          "def": "<ruby><rb>天皇</rb><rt>てんのう</rt></ruby>の<ruby><rb>男</rb><rt>おとこ</rt></ruby>の<ruby><rb>子</rb><rt>こ</rt></ruby>で、あとつぎになる<ruby><rb>皇子</rb><rt>おうじ</rt></ruby>。",
          "hyouki": [
            "皇太子"
          ]
        }
      ],
      "0005": [
        {
          "def": "<ruby><rb>日本</rb><rt>にっぽん</rt></ruby>で、<ruby><rb>年</rb><rt>とし</rt></ruby>につける<ruby><rb>呼</rb><rt>よ</rt></ruby>び<ruby><rb>名</rb><rt>な</rt></ruby>。<ruby><rb>元号</rb><rt>げんごう</rt></ruby>。<ruby><rb>平成</rb><rt>へいせい</rt></ruby>や<ruby><rb>昭和</rb><rt>しょうわ</rt></ruby>など。",
          "hyouki": [
            "年号"
          ]
        }
      ],
      "0006": [
        {
          "def": "<ruby><rb>国</rb><rt>くに</rt></ruby>の<ruby><rb>政治</rb><rt>せいじ</rt></ruby>を<ruby><rb>行</rb><rt>おこな</rt></ruby>うところ。",
          "hyouki": [
            "政府"
          ]
        },
        {
          "def": "<ruby><rb>内閣</rb><rt>ないかく</rt></ruby>。",
          "hyouki": [
            "政府"
          ]
        }
      ],
      "0007": [
        {
          "def": "<ruby><rb>国民</rb><rt>こくみん</rt></ruby>がみんなで<ruby><rb>祝</rb><rt>いわ</rt></ruby>う<ruby><rb>日</rb><rt>ひ</rt></ruby>。",
          "hyouki": [
            "祝日"
          ]
        }
      ],
      "0008": [
        {
          "def": "<ruby><rb>観光</rb><rt>かんこう</rt></ruby>やスポーツなどのために、<ruby><rb>団体</rb><rt>だんたい</rt></ruby>で<ruby><rb>行</rb><rt>い</rt></ruby>く<ruby><rb>旅行</rb><rt>りょこう</rt></ruby>。",
          "hyouki": [
            "ツアー"
          ]
        }
      ],
      "0009": [
        {
          "def": "<ruby><rb>時間</rb><rt>じかん</rt></ruby>を<ruby><rb>使</rb><rt>つか</rt></ruby>う。",
          "hyouki": [
            "過ごす"
          ]
        },
        {
          "def": "<ruby><rb>月日</rb><rt>つきひ</rt></ruby>を<ruby><rb>送</rb><rt>おく</rt></ruby>る。<ruby><rb>暮</rb><rt>く</rt></ruby>らす。",
          "hyouki": [
            "過ごす"
          ]
        },
        {
          "def": "<ruby><rb>程度</rb><rt>ていど</rt></ruby>をこす。",
          "hyouki": [
            "過ごす"
          ]
        },
        {
          "def": "そのままにしておく。",
          "hyouki": [
            "過ごす"
          ]
        }
      ],
      "0010": [
        {
          "def": "<ruby><rb>天皇</rb><rt>てんのう</rt></ruby>の<ruby><rb>家族</rb><rt>かぞく</rt></ruby>。",
          "hyouki": [
            "皇室"
          ]
        }
      ],
      "0011": [
        {
          "def": "<ruby><rb>国</rb><rt>くに</rt></ruby>や、<ruby><rb>地方公共団体</rb><rt>ちほうこうきょうだんたい</rt></ruby>の<ruby><rb>仕事</rb><rt>しごと</rt></ruby>をする<ruby><rb>所</rb><rt>ところ</rt></ruby>。<ruby><rb>官庁</rb><rt>かんちょう</rt></ruby>。<ruby><rb>役場</rb><rt>やくば</rt></ruby>。",
          "hyouki": [
            "役所"
          ]
        }
      ],
      "0012": [
        {
          "def": "<ruby><rb>仕組</rb><rt>しく</rt></ruby>み。<ruby><rb>組織</rb><rt>そしき</rt></ruby>。",
          "hyouki": [
            "システム"
          ]
        },
        {
          "def": "ひとまとまりの<ruby><rb>組</rb><rt>く</rt></ruby>み<ruby><rb>合</rb><rt>あ</rt></ruby>わせ。",
          "hyouki": [
            "システム"
          ]
        }
      ],
      "0013": [
        {
          "def": "<ruby><rb>始</rb><rt>はじ</rt></ruby>まる。",
          "hyouki": [
            "起こる"
          ]
        },
        {
          "def": "<ruby><rb>生</rb><rt>しょう</rt></ruby>じる。<ruby><rb>起</rb><rt>お</rt></ruby>きる。",
          "hyouki": [
            "起こる"
          ]
        }
      ],
      "0014": [
        {
          "def": "<ruby><rb>多</rb><rt>おお</rt></ruby>くの<ruby><rb>人</rb><rt>ひと</rt></ruby>に<ruby><rb>広</rb><rt>ひろ</rt></ruby>く<ruby><rb>知</rb><rt>し</rt></ruby>らせること。",
          "hyouki": [
            "発表"
          ]
        }
      ]
    }
  }
}
